{
  "timingMeasuredAt": "2026-02-11T12:27:09.367Z",
  "runner": "ubuntu-latest",
  "frameworkVersion": "2.49.4",
  "avgInstallTimeMs": 2195,
  "minInstallTimeMs": 1945,
  "maxInstallTimeMs": 2904,
  "nodeModulesSize": 95035392,
  "nodeModulesSizeProdOnly": 24576,
  "coldBuildTimeMs": 4220,
  "warmBuildTimeMs": 3910,
  "buildOutputSize": 1343488,
  "coldBuildTime": {
    "avgMs": 3981.2,
    "minMs": 3828,
    "maxMs": 4297
  },
  "warmBuildTime": {
    "avgMs": 3900.2,
    "minMs": 3870,
    "maxMs": 3974
  },
  "installTime": {
    "avgMs": 2111.4,
    "minMs": 1887,
    "maxMs": 2705
  }
}
